calculator_project_231023/__init__.py
calculator_project_231023/calculator.py
calculator_project_231023-1.0.8.dist-info/LICENSE
calculator_project_231023-1.0.8.dist-info/WHEEL
calculator_project_231023-1.0.8.dist-info/METADATA
calculator_project_231023-1.0.8.dist-info/RECORD
