Metadata-Version: 2.1
Name: calculator_project_231023
Version: 1.0.8
Summary: Calculator Project
Author-email: ramunen <info@ideacode.eu>
Requires-Python: >=3.10
Classifier: License :: OSI Approved :: MIT License
Project-URL: Home, https://github.com/ramunen/DWWP1Project
